[
    {
        "name": "boi", "start": "2024/9/20", "end": "2024/9/26", "country": "mk",
        "participants": {
            "emad_alharbi": "none",
            "muaath_alqarni": "none",
            "saad_alarifi": "none",
            "mohammed_bashkail": "none",
            "sultan_alaiban": "none",
            "mohammed_alasmari": "none"
        }
    },
    {
        "name": "egoi", "start": "2024/9/20", "end": "2024/9/26", "country": "nl",
        "participants": {
            "rifal_alhazmi": "hounarablemention",
            "basma_mansour": "hounarablemention",
            "mariah_alramadhan": "hounarablemention",
            "lamar_alhebshi": "hounarablemention"
        }
    },
    {
        "name": "apio", "start": "2024/5/18", "end": "2024/5/19", "country": "online",
        "participants": {
            "adeeb_alshehri": "silver",
            "ahmad_alhashim": "none",
            "muaath_alqarni": "none",
            "munther_alzayer": "none",
            "essa_almosa": "none",
            "mohammad_alyousef": "none",
            "emad_alharbi": "none",
            "saad_alarifi": "none"
        }
    },
    {
        "name": "jboi", "start": "2023/11/25", "end": "2023/11/28", "country": "online",
        "participants": {
            "abdulrahman_alghamdi": "bronze",
            "saad_alarifi": "hounarablemention",
            "abdullah_alodaibi": "none",
            "": "none"
        }
    },
    {
        "name": "boi", "start": "2023/10/29", "end": "2023/11/3", "country": "si",
        "participants": {
            "adeeb_alshehri": "bronze",
            "humaid_alhuthali": "hounarablemention",
            "emad_alharbi": "hounarablemention",
            "ahmad_alhashim": "hounarablemention",
            "essa_almosa": "hounarablemention",
            "rifal_alhazmi": "hounarablemention"
        }
    },
    {
        "name": "ioi", "start": "2023/8/7", "end": "2023/8/15", "country": "hu",
        "participants": {
            "humaid_alhuthali": "bronze",
            "adeeb_alshehri": "hounarablemention",
            "essa_almosa": "hounarablemention",
            "asdf": "none"
        }
    },
    {
        "name": "egoi", "start": "2023/7/15", "end": "2023/7/21", "country": "sw",
        "participants": {
            "rifal_alhazmi": "hounarablemention",
            "basma_mansour": "hounarablemention",
            "mariah_alramadhan": "hounarablemention",
            "lamar_alhebshi": "hounarablemention"
        }
    },
    {
        "name": "apio", "start": "2023/5/20", "end": "2023/5/20", "country": "online",
        "participants": {
            "adeeb_alshehri": "none",
            "emad_alharbi": "none",
            "muaath_alqarni": "none",
            "mohammad_alyousef": "none",
            "sultan_alaiban": "none",
            "mohammed_alasmari": "none"
        }
    },
    {
        "name": "egoi", "start": "2022/10/16", "end": "2022/10/23", "country": "tr",
        "participants": {
            "rifal_alhazmi": "hounarablemention",
            "basma_mansour": "hounarablemention",
            "mariah_alramadhan": "hounarablemention",
            "lamar_alhebshi": "hounarablemention"
        }
    },
    {
        "name": "ioi", "start": "2022/8/7", "end": "2022/8/15", "country": "id",
        "participants": {
            "abdulaziz_alshibli": "bronze",
            "adeeb_alshehri": "hounarablemention",
            "essa_almosa": "hounarablemention",
            "asdf": "none"
        }
    },
    {
        "name": "apio", "start": "2022/5/30", "end": "2022/5/30", "country": "online",
        "participants": {
            "adeeb_alshehri": "bronze",
            "abdulmohsen_mohammedsaleh": "bronze",
            "muaath_alqarni": "none",
            "mohammad_alyousef": "none",
            "sultan_alaiban": "none",
            "mohammed_alasmari": "none"
        }
    },
    {
        "name": "ioi", "start": "2021/6/19", "end": "2021/6/25", "country": "online",
        "participants": {
            "abdulaziz_alshibli": "bronze",
            "adeeb_alshehri": "hounarablemention",
            "essa_almosa": "hounarablemention",
            "asdf": "none"
        }
    },
    {
        "name": "apio", "start": "2021/5/26", "end": "2022/5/26", "country": "online",
        "participants": {
            "fares_basuni": "bronze",
            "abdulmohsen_mohammedsaleh": "none",
            "humaid_alhuthali": "none",
            "abdulaziz_alshibli": "none",
            "mohammed_alsaad": "none",
            "almothana_alzahrani": "none"
        }
    },
    {
        "name": "ioi", "start": "2020/6/19", "end": "2021/6/25", "country": "online",
        "participants": {
            "fares_basuni": "bronze",
            "humaid_alhuthali": "none",
            "almothana_alzahrani": "none",
            "adeeb_alshehri": "none"
        }
    },
    {
        "name": "ioi", "start": "2019/6/19", "end": "2019/6/25", "country": "az",
        "participants": {
            "fares_basuni": "bronze",
            "adsf": "hounarablemention",
            "asdfa": "hounarablemention",
            "asdfd": "none"
        }
    }
]